{
  "total": {
    "word_count_formatted": "21.6",
    "word_count_raw": 215503,
    "chinese_chars": 208747,
    "english_words": 6756,
    "posts_count": 125,
    "thoughts_count": 16
  },
  "this_year": {
    "word_count_formatted": "5.4",
    "word_count_raw": 54026,
    "chinese_chars": 52274,
    "english_words": 1752,
    "posts_count": 35,
    "thoughts_count": 15
  },
  "posts": {
    "count": 125,
    "word_count_formatted": "21.0",
    "word_count_raw": 209742,
    "chinese_chars": 203172,
    "english_words": 6570
  },
  "thoughts": {
    "count": 16,
    "word_count_formatted": "0.58",
    "word_count_raw": 5761,
    "chinese_chars": 5575,
    "english_words": 186
  },
  "generated_at": "",
  "last_updated": "2025-05-26"
}